showenv/__init__.py
showenv/__main__.py
showenv/showenv.py
showenv/scripts/config_env.txt
showenv/scripts/show_config_env.sh
showenv/scripts/show_structure_project.sh
showenv/scripts/structure_project.txt
showenv/scripts/test_env.py
showenv-2.0.data/scripts/config_env.txt
showenv-2.0.data/scripts/show_config_env.sh
showenv-2.0.data/scripts/show_structure_project.sh
showenv-2.0.data/scripts/structure_project.txt
showenv-2.0.data/scripts/test_env.py
showenv-2.0.dist-info/LICENSE
showenv-2.0.dist-info/METADATA
showenv-2.0.dist-info/WHEEL
showenv-2.0.dist-info/entry_points.txt
showenv-2.0.dist-info/top_level.txt
showenv-2.0.dist-info/RECORD
