Metadata-Version: 2.1
Name: showenv
Version: 2.0
Summary: Show informations about project, python, pip, libraries and OS
Home-page: https://github.com/brunocampos01/showenv
Author: brunocampos01
Author-email: brunocampos01@gmail.com
License: MIT
Platform: linux
Classifier: Programming Language :: Python
Classifier: Natural Language :: English
Classifier: License :: OSI Approved :: MIT License
License-File: LICENSE
Requires-Dist: click (==8.0.1)
Requires-Dist: distlib (==0.3.2)
Requires-Dist: filelock (==3.0.12)
Requires-Dist: pep517 (==0.11.0)
Requires-Dist: pip-tools (==6.2.0)
Requires-Dist: pyfiglet (==0.8.post1)
Requires-Dist: six (==1.16.0)
Requires-Dist: sty (==1.0.0b12)
Requires-Dist: tomli (==1.2.1)
Requires-Dist: virtualenv (==20.0.23)
Requires-Dist: wheel (==0.37.0)
